bdrcmodels/__init__.py
bdrcmodels/models.py
bdrcmodels-0.5.dist-info/LICENSE
bdrcmodels-0.5.dist-info/METADATA
bdrcmodels-0.5.dist-info/WHEEL
bdrcmodels-0.5.dist-info/top_level.txt
bdrcmodels-0.5.dist-info/RECORD
